[
	{
		"id": "1",
		"category": "Новини",
		"date": "20.12.2022",
		"views": 3,
		"title": "В Україні в 2016 році потрібно ввести медстрахування всіх громадян - прем'єр",
		"slug": "v-ukrayini-v-2016-rotsi-potribno-vvesti-medstrakhuvannya-vsikh-gromadyan-premier",
		"description": "<blockquote class='block-incut block-incut--left block-incut--text-small'><div class='block-incut__content'><div class='block-incut__text'><p>На сайте Всемирной организации здравоохранения <a href='http: //web.archive.org/web/20220731213557/' rel='nofollow noreferrer noopener' target='_blank'>указано</a>, что синдром Гийена-Барре — это редкое состояние, при котором иммунная система человека поражает собственные периферические нервы. Тяжелые случаи синдрома способны привести к полному параличу и несут потенциальную угрозу для жизни. Несмотря на это, большинство людей полностью выздоравливает даже в самых тяжёлых ситуациях, отмечает ВОЗ.</p></div></div></blockquote>",
		"imageUrl": "/photos/news/img_1.jpg",
		"reviews": 5,
		"likes": {
			"amount": 3,
			"liked": true
		}
	},
	{
		"id": "2",
		"category": "Новини",
		"date": "07.10.2022",
		"views": 0,
		"title": "Автомобілістам росії доведеться замінити всі поліси ОСАЦВ з 1 липня 2016 року",
		"slug": "avtomobilistam-rosiyi-dovedetsya-zaminiti-vsi-polisi-osatsv-z-1-lipnya-2016-roku",
		"description": "lorem ipsum dolor sit amet, consectetur adip",
		"imageUrl": "/photos/news/img_2.jpg",
		"reviews": 0,
		"likes": {
			"amount": 0,
			"liked": false
		}
	},
	{
		"id": "3",
		"category": "Новини",
		"date": "04.04.2022",
		"views": 0,
		"title": "Ліміти по ОСАЦВ в Україні будуть приведені до стандартів ЄС",
		"slug": "limiti-po-osatsv-v-ukrayini-budut-privedeni-do-standartiv-ies",
		"description": "lorem ipsum dolor sit amet, consectetur adip",
		"imageUrl": "/photos/news/img_3.jpg",
		"reviews": 0,
		"likes": {
			"amount": 0,
			"liked": false
		}
	},
	{
		"id": "4",
		"category": "Новини",
		"date": "18.02.2022",
		"views": 1,
		"title": "Ліміти по ОСАЦВ в Україні будуть приведені до стандартів ЄСC",
		"slug": "iti-po-osatsv-v-ukrayini-budut-privedeni-do-standartiv-iesc",
		"description": "lorem ipsum dolor sit amet, consectetur adip",
		"imageUrl": "/photos/news/img_4.jpg",
		"reviews": 0,
		"likes": {
			"amount": 0,
			"liked": false
		}
	},
	{
		"id": "5",
		"category": "Новини",
		"date": "10.12.2022",
		"views": 3,
		"title": "В Україні в 2016 році потрібно ввести медстрахування всіх громадян - прем'єрр",
		"slug": "v-ukrayini-v-2016-rotsi-potribno-vvesti-medstrakhuvannya-vsikh-gromadyan-premierr",
		"description": "lorem ipsum dolor sit amet, consectetur adip",
		"imageUrl": "/photos/news/img_1.jpg",
		"reviews": 5,
		"likes": {
			"amount": 3,
			"liked": true
		}
	}
]